Workbook

Sheet Dashboard
A1: Startup SWOT & PESTLE Strategic Analysis Dashboard
A3: Strategic feasibility, risk and growth-potential evaluation across a 100-startup case-study database | Prepared by Finance Veda Research
A5: Total Startups Analyzed | E5: Avg. Growth Potential Score | I5: Avg. Investment Attractiveness | M5: High-Risk Startups | Q5: Avg. Market Size ($M) | U5: Top Industry by Count
A7: =COUNTA(Data!A2:A101) -> 100 | E7: =ROUND(AVERAGE(Data!T2:T101),1) -> 5.6 | I7: =ROUND(AVERAGE(Scorecard!F2:F101),1) -> 5.2 | M7: =COUNTIF(Data!S2:S101,"High") -> 25 | Q7: =ROUND(AVERAGE(Data!G2:G101),1) -> 325.9 | U7: =INDEX(Calc!A2:A18,MATCH(MAX(Calc!B2:B18),Calc!B2:B18,0)) -> EdTech
B49: Strategic Insights & Recommendations
B51: 1. Technological and Economic factors carry the highest average PESTLE impact, signalling that tech-enabled, cost-efficient business models are best positioned for near-term growth.
B53: 2. 25% of startups in the database fall into the High-Risk band, concentrated in sectors with elevated competitive intensity and legal/regulatory exposure (FinTech, HealthTech, InsurTech).
B55: 3. EdTech and Logistics & Supply Chain are the most represented industries, indicating strong founder and investor interest, but also signalling rising competitive saturation.
B57: 4. Startups combining a high Growth Potential Score with a low-to-moderate Competitive Intensity Score (lower-right region empty in the strategic map) represent the most attractive whitespace for new entrants.
B59: 5. The top 10 startups by Investment Attractiveness Score skew toward Cybersecurity, SaaS, HealthTech and FinTech - sectors with strong technological moats and recurring revenue.
B61: 6. Environmental impact scores remain the lowest on average, suggesting most startups in the database are not yet building sustainability into their core proposition - a forward-looking differentiation opportunity.

Sheet Data
A1: Startup ID | B1: Startup Name | C1: Industry | D1: Product/Service | E1: Target Customer Segment | F1: Region | G1: Market Size Estimate ($M) | H1: Startup Strength | I1: Startup Weakness | J1: Market Opportunity | K1: Market Threat | L1: Political Impact Score | M1: Economic Impact Score | N1: Social Impact Score | O1: Technological Impact Score | P1: Legal Impact Score | Q1: Environmental Impact Score | R1: Competitive Intensity Score | S1: Risk Level | T1: Growth Potential Score
A2: ST001 | B2: FreshBite Solutions | C2: FoodTech | D2: Restaurant inventory & POS SaaS | E2: Urban Professionals | F2: Bengaluru | G2: 107 | H2: Strategic partnerships with established players | I2: High customer churn beyond the trial period | J2: Growing disposable income among target segment | K2: Economic slowdown impacting discretionary spending | L2: 1 | M2: 6 | N2: 7 | O2: 7 | P2: 6 | Q2: 5 | R2: 6 | S2: Medium | T2: 6
A3: ST002 | B3: BrightPath Labs | C3: EdTech | D3: Live doubt-solving tutoring app | E3: Tier-2/3 City Students | F3: Southeast Asia | G3: 391.3 | H3: Strong data network effects improving with scale | I3: Limited working capital for aggressive scaling | J3: New regulatory framework opening up the category | K3: Regulatory uncertainty around the sector's framework | L3: 4 | M3: 3 | N3: 6 | O3: 9 | P3: 6 | Q3: 3 | R3: 7 | S3: Medium | T3: 6
A4: ST003 | B4: NutriNest Labs | C4: FoodTech | D4: Organic food delivery platform | E4: Health-conscious Consumers | F4: Bengaluru | G4: 567.7 | H4: Strategic partnerships with established players | I4: Limited working capital for aggressive scaling | J4: Favourable government incentives for the sector | K4: Rapid technology obsolescence and platform shifts | L4: 3 | M4: 4 | N4: 6 | O4: 6 | P4: 4 | Q4: 4 | R4: 10 | S4: Medium | T4: 5
A5: ST004 | B5: JurisRoot Technologies | C5: LegalTech | D5: Lawyer marketplace & consultation app | E5: SMEs | F5: Kolkata | G5: 153.4 | H5: High customer retention and repeat usage | I5: Unproven scalability of core technology | J5: Rising smartphone and internet penetration | K5: Imitable business model with low switching costs | L5: 3 | M5: 2 | N5: 4 | O5: 5 | P5: 10 | Q5: 3 | R5: 2 | S5: Medium | T5: 2
A6: ST005 | B6: InferNest | C6: AI/ML | D6: Conversational AI customer support bot | E6: Job Seekers | F6: Mumbai | G6: 67.5 | H6: High employee retention and strong culture | I6: High customer acquisition cost relative to LTV | J6: Growing disposable income among target segment | K6: Rapid technology obsolescence and platform shifts | L6: 4 | M6: 6 | N6: 5 | O6: 10 | P6: 6 | Q6: 5 | R6: 6 | S6: Medium | T6: 6
A7: ST006 | B7: ChargeNova | C7: CleanTech/EV | D7: Battery-swapping infrastructure | E7: Logistics Companies | F7: Mumbai | G7: 303.4 | H7: Experienced advisory board and mentor network | I7: Low average revenue per user (ARPU) | J7: Growing disposable income among target segment | K7: Economic slowdown impacting discretionary spending | L7: 9 | M7: 4 | N7: 7 | O7: 8 | P7: 4 | Q7: 10 | R7: 6 | S7: Medium | T7: 6
A8: ST007 | B8: PeopleNest | C8: HR Tech | D8: Employee benefits & payroll fintech | E8: Enterprise Clients | F8: Tier-2/3 Cities (India) | G8: 587.1 | H8: Lean cost structure with healthy unit economics | I8: Founder-dependent decision making and operations | J8: Partnership potential with large enterprise clients | K8: Economic slowdown impacting discretionary spending | L8: 2 | M8: 3 | N8: 6 | O8: 8 | P8: 6 | Q8: 1 | R8: 7 | S8: Medium | T8: 7
A9: ST008 | B9: JurisRoot Solutions | C9: LegalTech | D9: Contract lifecycle management SaaS | E9: SMEs | F9: Kolkata | G9: 354.7 | H9: Diversified and recurring revenue streams | I9: High customer acquisition cost relative to LTV | J9: Consolidation opportunities via M&A of smaller players | K9: Tightening data localisation and compliance norms | L9: 5 | M9: 2 | N9: 3 | O9: 6 | P9: 9 | Q9: 1 | R9: 6 | S9: High | T9: 2
A10: ST009 | B10: ArenaRoot Networks | C10: Gaming & Esports | D10: Mobile fantasy sports platform | E10: College Students | F10: Kolkata | G10: 30.6 | H10: Lean cost structure with healthy unit economics | I10: Thin operating margins in early growth phase | J10: Partnership potential with large enterprise clients | K10: Talent attrition to larger, better-funded competitors | L10: 1 | M10: 6 | N10: 7 | O10: 6 | P10: 3 | Q10: 3 | R10: 7 | S10: Low | T10: 4
A11: ST010 | B11: MoneyMint Technologies | C11: FinTech | D11: UPI-based micro-lending app | E11: Unbanked Population | F11: Ahmedabad | G11: 368.1 | H11: Strategic partnerships with established players | I11: Founder-dependent decision making and operations | J11: Increasing demand for digital-first solutions | K11: Heavy dependence on third-party aggregator platforms | L11: 4 | M11: 7 | N11: 5 | O11: 7 | P11: 7 | Q11: 1 | R11: 7 | S11: Medium | T11: 6
A12: ST011 | B12: MartRoot | C12: E-commerce | D12: B2B wholesale ordering app | E12: Small Retailers | F12: North America | G12: 71.8 | H12: High employee retention and strong culture | I12: Thin operating margins in early growth phase | J12: Largely untapped rural and semi-urban market | K12: High customer price sensitivity limiting monetisation | L12: 6 | M12: 5 | N12: 8 | O12: 7 | P12: 4 | Q12: 3 | R12: 8 | S12: Medium | T12: 5
A13: ST012 | B13: PolicyLoop | C13: InsurTech | D13: Micro-insurance distribution platform | E13: Urban Millennials | F13: Tier-2/3 Cities (India) | G13: 33.4 | H13: Strong data network effects improving with scale | I13: Limited data history for risk/credit modelling | J13: Rising smartphone and internet penetration | K13: Potential entry of large global players into the market | L13: 4 | M13: 5 | N13: 7 | O13: 6 | P13: 8 | Q13: 4 | R13: 5 | S13: Medium | T13: 4
... A101: ST100 | B101: AgroVerve 58 | C101: AgriTech | D101: Crop insurance & advisory platform | E101: Agri-input Retailers | F101: Bengaluru | G101: 539 | H101: High customer retention and repeat usage | I101: Limited brand awareness outside core markets | J101: Favourable government incentives for the sector | K101: Input cost / currency volatility impacting margins | L101: 6 | M101: 6 | N101: 5 | O101: 3 | P101: 6 | Q101: 6 | R101: 2 | S101: Low | T101: 6

Sheet Scorecard
A1: Startup ID | B1: Startup Name | C1: Industry | D1: PESTLE Impact Score | E1: Startup Viability Score | F1: Investment Attractiveness Score | G1: Market Readiness Score | H1: Rank Key
A2: =Data!A2 -> ST001 | B2: =Data!B2 -> FreshBite Solutions | C2: =Data!C2 -> FoodTech | D2: =AVERAGE(Data!L2:Q2) -> 5.3333333 | E2: =ROUND((0.4*Data!T2+0.35*(10-Data!R2)+0.25*D2),1) -> 5.1 | F2: =ROUND((0.4*Data!T2+0.35*E2+0.25*MIN(10,Data!G2/65)),1) -> 4.6 | G2: =ROUND(AVERAGE(Data!M2,Data!N2,Data!O2),1) -> 6.7 | H2: =F2+ROW()/100000 -> 4.60002
A3: =Data!A3 -> ST002 | B3: =Data!B3 -> BrightPath Labs | C3: =Data!C3 -> EdTech | D3: =AVERAGE(Data!L3:Q3) -> 5.1666667 | E3: =ROUND((0.4*Data!T3+0.35*(10-Data!R3)+0.25*D3),1) -> 4.7 | F3: =ROUND((0.4*Data!T3+0.35*E3+0.25*MIN(10,Data!G3/65)),1) -> 5.6 | G3: =ROUND(AVERAGE(Data!M3,Data!N3,Data!O3),1) -> 6 | H3: =F3+ROW()/100000 -> 5.60003
A4: =Data!A4 -> ST003 | B4: =Data!B4 -> NutriNest Labs | C4: =Data!C4 -> FoodTech | D4: =AVERAGE(Data!L4:Q4) -> 4.5 | E4: =ROUND((0.4*Data!T4+0.35*(10-Data!R4)+0.25*D4),1) -> 3.1 | F4: =ROUND((0.4*Data!T4+0.35*E4+0.25*MIN(10,Data!G4/65)),1) -> 5.3 | G4: =ROUND(AVERAGE(Data!M4,Data!N4,Data!O4),1) -> 5.3 | H4: =F4+ROW()/100000 -> 5.30004
A5: =Data!A5 -> ST004 | B5: =Data!B5 -> JurisRoot Technologies | C5: =Data!C5 -> LegalTech | D5: =AVERAGE(Data!L5:Q5) -> 4.5 | E5: =ROUND((0.4*Data!T5+0.35*(10-Data!R5)+0.25*D5),1) -> 4.7 | F5: =ROUND((0.4*Data!T5+0.35*E5+0.25*MIN(10,Data!G5/65)),1) -> 3 | G5: =ROUND(AVERAGE(Data!M5,Data!N5,Data!O5),1) -> 3.7 | H5: =F5+ROW()/100000 -> 3.00005
A6: =Data!A6 -> ST005 | B6: =Data!B6 -> InferNest | C6: =Data!C6 -> AI/ML | D6: =AVERAGE(Data!L6:Q6) -> 6 | E6: =ROUND((0.4*Data!T6+0.35*(10-Data!R6)+0.25*D6),1) -> 5.3 | F6: =ROUND((0.4*Data!T6+0.35*E6+0.25*MIN(10,Data!G6/65)),1) -> 4.5 | G6: =ROUND(AVERAGE(Data!M6,Data!N6,Data!O6),1) -> 7 | H6: =F6+ROW()/100000 -> 4.50006
A7: =Data!A7 -> ST006 | B7: =Data!B7 -> ChargeNova | C7: =Data!C7 -> CleanTech/EV | D7: =AVERAGE(Data!L7:Q7) -> 7 | E7: =ROUND((0.4*Data!T7+0.35*(10-Data!R7)+0.25*D7),1) -> 5.6 | F7: =ROUND((0.4*Data!T7+0.35*E7+0.25*MIN(10,Data!G7/65)),1) -> 5.5 | G7: =ROUND(AVERAGE(Data!M7,Data!N7,Data!O7),1) -> 6.3 | H7: =F7+ROW()/100000 -> 5.50007
A8: =Data!A8 -> ST007 | B8: =Data!B8 -> PeopleNest | C8: =Data!C8 -> HR Tech | D8: =AVERAGE(Data!L8:Q8) -> 4.3333333 | E8: =ROUND((0.4*Data!T8+0.35*(10-Data!R8)+0.25*D8),1) -> 4.9 | F8: =ROUND((0.4*Data!T8+0.35*E8+0.25*MIN(10,Data!G8/65)),1) -> 6.8 | G8: =ROUND(AVERAGE(Data!M8,Data!N8,Data!O8),1) -> 5.7 | H8: =F8+ROW()/100000 -> 6.80008
A9: =Data!A9 -> ST008 | B9: =Data!B9 -> JurisRoot Solutions | C9: =Data!C9 -> LegalTech | D9: =AVERAGE(Data!L9:Q9) -> 4.3333333 | E9: =ROUND((0.4*Data!T9+0.35*(10-Data!R9)+0.25*D9),1) -> 3.3 | F9: =ROUND((0.4*Data!T9+0.35*E9+0.25*MIN(10,Data!G9/65)),1) -> 3.3 | G9: =ROUND(AVERAGE(Data!M9,Data!N9,Data!O9),1) -> 3.7 | H9: =F9+ROW()/100000 -> 3.30009
A10: =Data!A10 -> ST009 | B10: =Data!B10 -> ArenaRoot Networks | C10: =Data!C10 -> Gaming & Esports | D10: =AVERAGE(Data!L10:Q10) -> 4.3333333 | E10: =ROUND((0.4*Data!T10+0.35*(10-Data!R10)+0.25*D10),1) -> 3.7 | F10: =ROUND((0.4*Data!T10+0.35*E10+0.25*MIN(10,Data!G10/65)),1) -> 3 | G10: =ROUND(AVERAGE(Data!M10,Data!N10,Data!O10),1) -> 6.3 | H10: =F10+ROW()/100000 -> 3.0001
A11: =Data!A11 -> ST010 | B11: =Data!B11 -> MoneyMint Technologies | C11: =Data!C11 -> FinTech | D11: =AVERAGE(Data!L11:Q11) -> 5.1666667 | E11: =ROUND((0.4*Data!T11+0.35*(10-Data!R11)+0.25*D11),1) -> 4.7 | F11: =ROUND((0.4*Data!T11+0.35*E11+0.25*MIN(10,Data!G11/65)),1) -> 5.5 | G11: =ROUND(AVERAGE(Data!M11,Data!N11,Data!O11),1) -> 6.3 | H11: =F11+ROW()/100000 -> 5.50011
A12: =Data!A12 -> ST011 | B12: =Data!B12 -> MartRoot | C12: =Data!C12 -> E-commerce | D12: =AVERAGE(Data!L12:Q12) -> 5.5 | E12: =ROUND((0.4*Data!T12+0.35*(10-Data!R12)+0.25*D12),1) -> 4.1 | F12: =ROUND((0.4*Data!T12+0.35*E12+0.25*MIN(10,Data!G12/65)),1) -> 3.7 | G12: =ROUND(AVERAGE(Data!M12,Data!N12,Data!O12),1) -> 6.7 | H12: =F12+ROW()/100000 -> 3.70012
A13: =Data!A13 -> ST012 | B13: =Data!B13 -> PolicyLoop | C13: =Data!C13 -> InsurTech | D13: =AVERAGE(Data!L13:Q13) -> 5.6666667 | E13: =ROUND((0.4*Data!T13+0.35*(10-Data!R13)+0.25*D13),1) -> 4.8 | F13: =ROUND((0.4*Data!T13+0.35*E13+0.25*MIN(10,Data!G13/65)),1) -> 3.4 | G13: =ROUND(AVERAGE(Data!M13,Data!N13,Data!O13),1) -> 6 | H13: =F13+ROW()/100000 -> 3.40013
... A101: =Data!A101 -> ST100 | B101: =Data!B101 -> AgroVerve 58 | C101: =Data!C101 -> AgriTech | D101: =AVERAGE(Data!L101:Q101) -> 5.3333333 | E101: =ROUND((0.4*Data!T101+0.35*(10-Data!R101)+0.25*D101),1) -> 6.5 | F101: =ROUND((0.4*Data!T101+0.35*E101+0.25*MIN(10,Data!G101/65)),1) -> 6.7 | G101: =ROUND(AVERAGE(Data!M101,Data!N101,Data!O101),1) -> 4.7 | H101: =F101+ROW()/100000 -> 6.70101

Sheet Calc
A1: Industry | B1: Count | D1: Risk Level | E1: Count | G1: PESTLE Factor | H1: Average Score | J1: Rank | K1: Startup Name | L1: Investment Attractiveness | N1: Region | O1: Avg Market Size
A2: EdTech | B2: =COUNTIF(Data!$C$2:$C$101,A2) -> 8 | D2: Low | E2: =COUNTIF(Data!$S$2:$S$101,D2) -> 19 | G2: Political | H2: =ROUND(AVERAGE(Data!$L$2:$L$101),2) -> 4.66 | J2: 1 | K2: =INDEX(Scorecard!$B$2:$B$101,MATCH(L2,Scorecard!$H$2:$H$101,0)) -> GuardMesh Technologies | L2: =LARGE(Scorecard!$H$2:$H$101,1) -> 8.5004 | N2: Delhi NCR | O2: =IFERROR(ROUND(AVERAGEIF(Data!$F$2:$F$101,N2,Data!$G$2:$G$101),1),0) -> 420.2
A3: FinTech | B3: =COUNTIF(Data!$C$2:$C$101,A3) -> 5 | D3: Medium | E3: =COUNTIF(Data!$S$2:$S$101,D3) -> 56 | G3: Economic | H3: =ROUND(AVERAGE(Data!$M$2:$M$101),2) -> 5.5 | J3: 2 | K3: =INDEX(Scorecard!$B$2:$B$101,MATCH(L3,Scorecard!$H$2:$H$101,0)) -> OpsRoot | L3: =LARGE(Scorecard!$H$2:$H$101,2) -> 8.20029 | N3: Mumbai | O3: =IFERROR(ROUND(AVERAGEIF(Data!$F$2:$F$101,N3,Data!$G$2:$G$101),1),0) -> 293.6
A4: HealthTech | B4: =COUNTIF(Data!$C$2:$C$101,A4) -> 7 | D4: High | E4: =COUNTIF(Data!$S$2:$S$101,D4) -> 25 | G4: Social | H4: =ROUND(AVERAGE(Data!$N$2:$N$101),2) -> 5.59 | J4: 3 | K4: =INDEX(Scorecard!$B$2:$B$101,MATCH(L4,Scorecard!$H$2:$H$101,0)) -> MartRoot 69 | L4: =LARGE(Scorecard!$H$2:$H$101,3) -> 7.60065 | N4: Bengaluru | O4: =IFERROR(ROUND(AVERAGEIF(Data!$F$2:$F$101,N4,Data!$G$2:$G$101),1),0) -> 297.7
A5: AgriTech | B5: =COUNTIF(Data!$C$2:$C$101,A5) -> 7 | G5: Technological | H5: =ROUND(AVERAGE(Data!$O$2:$O$101),2) -> 6.67 | J5: 4 | K5: =INDEX(Scorecard!$B$2:$B$101,MATCH(L5,Scorecard!$H$2:$H$101,0)) -> MindMesh Networks | L5: =LARGE(Scorecard!$H$2:$H$101,4) -> 7.40088 | N5: Pune | O5: =IFERROR(ROUND(AVERAGEIF(Data!$F$2:$F$101,N5,Data!$G$2:$G$101),1),0) -> 424.3
A6: CleanTech/EV | B6: =COUNTIF(Data!$C$2:$C$101,A6) -> 6 | G6: Legal | H6: =ROUND(AVERAGE(Data!$P$2:$P$101),2) -> 5.74 | J6: 5 | K6: =INDEX(Scorecard!$B$2:$B$101,MATCH(L6,Scorecard!$H$2:$H$101,0)) -> JurisRoot | L6: =LARGE(Scorecard!$H$2:$H$101,5) -> 7.40018 | N6: Hyderabad | O6: =IFERROR(ROUND(AVERAGEIF(Data!$F$2:$F$101,N6,Data!$G$2:$G$101),1),0) -> 385.7
A7: E-commerce | B7: =COUNTIF(Data!$C$2:$C$101,A7) -> 5 | G7: Environmental | H7: =ROUND(AVERAGE(Data!$Q$2:$Q$101),2) -> 3.94 | J7: 6 | K7: =INDEX(Scorecard!$B$2:$B$101,MATCH(L7,Scorecard!$H$2:$H$101,0)) -> CarePulse Labs | L7: =LARGE(Scorecard!$H$2:$H$101,6) -> 7.3009 | N7: Chennai | O7: =IFERROR(ROUND(AVERAGEIF(Data!$F$2:$F$101,N7,Data!$G$2:$G$101),1),0) -> 440.9
A8: FoodTech | B8: =COUNTIF(Data!$C$2:$C$101,A8) -> 7 | J8: 7 | K8: =INDEX(Scorecard!$B$2:$B$101,MATCH(L8,Scorecard!$H$2:$H$101,0)) -> WorkNova Labs | L8: =LARGE(Scorecard!$H$2:$H$101,7) -> 7.20095 | N8: Kolkata | O8: =IFERROR(ROUND(AVERAGEIF(Data!$F$2:$F$101,N8,Data!$G$2:$G$101),1),0) -> 257.4
A9: Logistics & Supply Chain | B9: =COUNTIF(Data!$C$2:$C$101,A9) -> 8 | J9: 8 | K9: =INDEX(Scorecard!$B$2:$B$101,MATCH(L9,Scorecard!$H$2:$H$101,0)) -> OpsRoot 78 | L9: =LARGE(Scorecard!$H$2:$H$101,8) -> 7.10097 | N9: Ahmedabad | O9: =IFERROR(ROUND(AVERAGEIF(Data!$F$2:$F$101,N9,Data!$G$2:$G$101),1),0) -> 420.4
A10: SaaS / Enterprise Software | B10: =COUNTIF(Data!$C$2:$C$101,A10) -> 7 | J10: 9 | K10: =INDEX(Scorecard!$B$2:$B$101,MATCH(L10,Scorecard!$H$2:$H$101,0)) -> SafeNest Solutions | L10: =LARGE(Scorecard!$H$2:$H$101,9) -> 7.10094 | N10: Jaipur | O10: =IFERROR(ROUND(AVERAGEIF(Data!$F$2:$F$101,N10,Data!$G$2:$G$101),1),0) -> 106.9
A11: AI/ML | B11: =COUNTIF(Data!$C$2:$C$101,A11) -> 4 | J11: 10 | K11: =INDEX(Scorecard!$B$2:$B$101,MATCH(L11,Scorecard!$H$2:$H$101,0)) -> WealthBee Networks | L11: =LARGE(Scorecard!$H$2:$H$101,10) -> 7.10044 | N11: Pan-India | O11: =IFERROR(ROUND(AVERAGEIF(Data!$F$2:$F$101,N11,Data!$G$2:$G$101),1),0) -> 407.7
A12: Cybersecurity | B12: =COUNTIF(Data!$C$2:$C$101,A12) -> 6 | N12: Tier-2/3 Cities (India) | O12: =IFERROR(ROUND(AVERAGEIF(Data!$F$2:$F$101,N12,Data!$G$2:$G$101),1),0) -> 226.6
A13: PropTech | B13: =COUNTIF(Data!$C$2:$C$101,A13) -> 4 | N13: Southeast Asia | O13: =IFERROR(ROUND(AVERAGEIF(Data!$F$2:$F$101,N13,Data!$G$2:$G$101),1),0) -> 313.9
A14: TravelTech | B14: =COUNTIF(Data!$C$2:$C$101,A14) -> 5 | N14: North America | O14: =IFERROR(ROUND(AVERAGEIF(Data!$F$2:$F$101,N14,Data!$G$2:$G$101),1),0) -> 278.3
A15: Gaming & Esports | B15: =COUNTIF(Data!$C$2:$C$101,A15) -> 7 | N15: Europe | O15: =IFERROR(ROUND(AVERAGEIF(Data!$F$2:$F$101,N15,Data!$G$2:$G$101),1),0) -> 469.8
A16: InsurTech | B16: =COUNTIF(Data!$C$2:$C$101,A16) -> 5 | N16: Middle East | O16: =IFERROR(ROUND(AVERAGEIF(Data!$F$2:$F$101,N16,Data!$G$2:$G$101),1),0) -> 327.8
A17: LegalTech | B17: =COUNTIF(Data!$C$2:$C$101,A17) -> 4
A18: HR Tech | B18: =COUNTIF(Data!$C$2:$C$101,A18) -> 5
